<?xml version="1.0" encoding="UTF-8" standalone="yes"?>
<addon id="repository.batch.se"	
		name="Batch XBMC Add-ons" 
		version="1.0.1"
		provider-name="Batch">
	<extension point="xbmc.addon.repository"
		name="Batch XBMC Add-on Repository">
		<info compressed="true">https://github.com/downloads/batchen/Batch-XBMC/addons.xml</info>
		<checksum>https://github.com/downloads/batchen/Batch-XBMC/addons.xml.md5</checksum>
		<datadir zip="true">https://github.com/downloads/batchen/Batch-XBMC/</datadir>
	</extension>
	<extension point="xbmc.addon.metadata">
		<summary>Install Add-ons created by Batch</summary>
		<description>Download and install Add-ons created by Batch</description>
		<platform>all</platform>
	</extension>
</addon>
